DVD-EL/fa.v
/*
module to implement the full adder
*/

module FA (
    output sout,
    output cout,
    input a,
    input b,
    input cin
);

    assign sout = (a ^ b ^ cin);
    assign cout = ((a & b) | (b & cin) | (a & cin) );
    
endmodule

DVD-EL/fa_tb.v
`timescale 1ns/1ns
`include "fa.v"

module fa_tb;
wire sout;
wire cout;
reg a;
reg b;
reg cin;

FA full_adder(sout, cout, a, b, cin);

initial begin
    $dumpfile("fa_tb.vcd");
    $dumpvars(0, fa_tb);

    a = 1'b0; b = 1'b0; cin = 1'b0;
    #20;

    a = 1'b0; b = 1'b0; cin = 1'b1;
    #20;

    a = 1'b0; b = 1'b1; cin = 1'b0;
    #20;

    a = 1'b0; b = 1'b1; cin = 1'b1;
    #20;

    a = 1'b1; b = 1'b0; cin = 1'b0;
    #20;

    a = 1'b1; b = 1'b0; cin = 1'b1;
    #20;

    a = 1'b1; b = 1'b1; cin = 1'b0;
    #20;

    a = 1'b1; b = 1'b1; cin = 1'b1;
    #20;

    $display("Test complete!");
    $finish;
end

endmodule;

DVD-EL/fa_tb.vcd
$date
	Tue Mar 05 21:58:07 2024
$end
$version
	Icarus Verilog
$end
$timescale
	1ns
$end
$scope module fa_tb $end
$var wire 1 ! sout $end
$var wire 1 " cout $end
$var reg 1 # a $end
$var reg 1 $ b $end
$var reg 1 % cin $end
$scope module full_adder $end
$var wire 1 # a $end
$var wire 1 $ b $end
$var wire 1 % cin $end
$var wire 1 " cout $end
$var wire 1 ! sout $end
$upscope $end
$upscope $end
$enddefinitions $end
$comment Show the parameter values. $end
$dumpall
$end
#0
$dumpvars
0%
0$
0#
0"
0!
$end
#20
1!
1%
#40
0%
1$
#60
1"
0!
1%
#80
0"
1!
0%
0$
1#
#100
1"
0!
1%
#120
0%
1$
#140
1!
1%
