Control/CONTROL_R.v
/*
The module depicts the control unit of the processor. 
The control unit takes in the opcode, funct7 and funct3 as the inputs and determines the control register write in 
the IFU and the ALU control in the ALU for the proper execution of the instruction

The module outputs control instructions for-
1) R-type instructions (Register Type intructions)
2) U-type instructions 
3) J-type instructions
4) I-type instructions
5) S-type instructions
6) B-type instructions

the signal inst_type gives information of the encoding of the instruction. 

inst_type       |       Encoding
3'b000                  R
3'b001                  U
3'b010                  J
3'b011                  I
3'b100                  S
3'b101                  B

*/


module CONTROL_R(
    input[31:0] instruction_word,
    output reg[3:0] alu_ctrl,
    output reg shamt_en,        // control strobe for shift amount for I-type instructions
    output reg[2:0] branch_ctrl, 
    output reg jump_ctrl,       // control strobe to indicate JUMP instruction
    output reg reg_write,
    output reg[2:0] inst_type
);
    
    always@(instruction_word)
        begin
            
            // default initialization of output control signals to xxxx
            alu_ctrl = 4'bxxxx;
            shamt_en = 1'bx;
            branch_ctrl = 3'bxxx;
            jump_ctrl = 1'bx;

            //coding for R type instructions
            if(instruction_word[6:0] == 7'b0110011) begin
                reg_write = 1;
                inst_type = 3'b000;

                case(instruction_word[14:12])
                    3'b000 : begin
                        if(instruction_word[31:25] == 7'b0000000)
                            alu_ctrl = 4'b0010;     // ADD
                        else if(instruction_word[31:25] == 7'b0100000)
                            alu_ctrl = 4'b0100;     // SUB        
                    end 

                    3'b001 : alu_ctrl = 4'b0011;    // SLL (Shift Left Logical)
                    3'b010 : alu_ctrl = 4'b1000;    // SLT (Set Less Than)
                    3'b100 : alu_ctrl = 4'b0111;    // XOR (Bitwise XOR)
                    3'b101 : begin
                        if(instruction_word[31:25] == 7'b0000000)
                            alu_ctrl = 4'b0101;    // SRL (Shift Right Logical)
                        else if(instruction_word[31:25] == 7'b0100000)
                            alu_ctrl = 4'b1001;     // SRA (Shift Right Arithemetic)
                    end
                    3'b110 : alu_ctrl = 4'b0001;    // OR (Bitwise OR)
                    3'b111 : alu_ctrl = 4'b0000;    // AND (Bitwise AND)
                    
                endcase
            end
            
            
            /*
            else if(instruction_word[6:0] == 7'b0000011)
                begin
                    reg_write = 1'b1;
                    //r_or_w = 1'b0;      // write operation to store value enabled (LUI and AUIPC)
                    inst_type = 3'b011;
                end
                */
            
            // coding for I-type instructions
            else if(instruction_word[6:0] == 7'b0000011)
                begin
                    reg_write = 1'b1;
                    inst_type = 3'b011;
                    shamt_en = 1'b0;
                    alu_ctrl = 4'b0000;

                    case(instruction_word[14:12])
                        3'b000 : alu_ctrl = 4'b0010;
                        3'b001 : begin
                            alu_ctrl = 4'b0011;
                            shamt_en = 1'b1;
                        end
                        3'b010 : alu_ctrl = 4'b1000;
                        3'b011 : alu_ctrl = 4'b0111;
                        3'b100 : alu_ctrl = 4'b0001;
                        3'b101 : begin
                            shamt_en = 1'b1;
                            if(instruction_word[31:25] == 7'b0000000)
                                assign alu_ctrl = 4'b0101;
                            else if(instruction_word[31:25] == 7'b0100000)
                                assign alu_ctrl = 4'b1001;
                        end
                        3'b110 : alu_ctrl = 4'b0001;
                        3'b111 : alu_ctrl = 4'b0010;
                    endcase

                end
            
            // coding for U-type instructions
            else if(instruction_word[6:0] == 7'b0110111)
                begin
                    inst_type = 3'b001;
                    //alu_ctrl = 4'bxxxx;
                    alu_ctrl = 4'b0011;
                end
            
            // coding for S-type instructions
            else if(instruction_word[6:0] == 7'b0100011)
                begin
                    inst_type = 3'b100;    
                end
            
            // coding for B-type instructions
            else if(instruction_word[6:0] == 7'b1100011)
                begin
                    inst_type = 3'b101;
                    branch_ctrl = 3'bxxx;       // initialise to default for every instruction

                    case(instruction_word[14:12])
                        3'b000 : branch_ctrl = 3'b000;      // BEQ  (Branch if Equal)
                        3'b001 : branch_ctrl = 3'b001;      // BNE  (Branch if Not Equal)
                        3'b100 : branch_ctrl = 3'b010;      // BLT  (Branch if Less Than)
                        3'b101 : branch_ctrl = 3'b011;      // BGE  (Branch if Greater than)
                        3'b110 : branch_ctrl = 3'b100;      // BLTU (Branch if Less than (unsigned comparison))
                        3'b111 : branch_ctrl = 3'b101;      // BGEU (Branch if Greater than (unsigned comparison))
                    endcase


                end
            
            // coding for J type instructions
            else if(instruction_word[6:0] == 7'b1101111)
                begin
                    inst_type = 3'b010;
                    jump_ctrl = 1'b1;

                end


                
        end

endmodule

Control/CONTROL_R_tb.v
`timescale 1ns/1ns
`include "CONTROL_R.v"

module CONTROL_R_tb;
reg[31:0] instruction_word;
wire[3:0] alu_ctrl;
wire shamt_en;
wire[2:0] branch_ctrl;
wire jump_ctrl;
wire reg_write;
wire[2:0] inst_type;

CONTROL_R control_unit (
    .instruction_word(instruction_word),
    .alu_ctrl(alu_ctrl),
    .shamt_en(shamt_en),
    .branch_ctrl(branch_ctrl),
    .jump_ctrl(jump_ctrl),
    .reg_write(reg_write),
    .inst_type(inst_type)
);

/*
initial
    begin
        assign instruction_word = 32'b0;
    end
*/

initial
begin
    $dumpfile("CONTROL_R_tb.vcd");
    $dumpvars(0, CONTROL_R_tb);

    // R type instructions testing
    instruction_word = 32'b0000000_00100_10101_000_00101_0110011;
    #20;

    instruction_word = 32'b0100000_00101_10101_000_00110_0110011;
    #20;

    instruction_word = 32'b0000000_00100_10101_001_00101_0110011;
    #20;

    // I type instructions testing
    instruction_word = 32'b001000001001_10011_000_00111_0000011;
    #20;

    instruction_word = 32'b011101101101_00001_111_00110_0000011;
    #20;

    instruction_word = 32'b000011110101_01101_101_01101_0000011;
    #20;

    instruction_word = 32'b000011110101_01101_011_01101_0000011;
    #20;

    // U-type instructions
    instruction_word = 32'b00001111010101101011_01101_0110111;
    #20;

    // S-type instructions
    instruction_word = 32'b0000111_10101_01101_010_01101_0100011;
    #20;

    // B-type instructions
    instruction_word = 32'b0000111_10101_01101_111_01101_1100011;
    #20;

    instruction_word = 32'b0000111_10101_01101_100_01101_1100011;
    #20;

    // J-type instructions
    instruction_word = 32'b0000111_10101_01101_111_01101_1101111;
    #20;

    $display("Test Complete");
    $finish;
end

endmodule

Control/CONTROL_R_tb.vcd
$date
	Fri Mar 01 21:31:36 2024
$end
$version
	Icarus Verilog
$end
$timescale
	1ns
$end
$scope module CONTROL_R_tb $end
$var wire 1 ! shamt_en $end
$var wire 1 " reg_write $end
$var wire 1 # jump_ctrl $end
$var wire 3 $ inst_type [2:0] $end
$var wire 3 % branch_ctrl [2:0] $end
$var wire 4 & alu_ctrl [3:0] $end
$var reg 32 ' instruction_word [31:0] $end
$scope module control_unit $end
$var wire 32 ( instruction_word [31:0] $end
$var reg 4 ) alu_ctrl [3:0] $end
$var reg 3 * branch_ctrl [2:0] $end
$var reg 3 + inst_type [2:0] $end
$var reg 1 # jump_ctrl $end
$var reg 1 " reg_write $end
$var reg 1 ! shamt_en $end
$upscope $end
$upscope $end
$enddefinitions $end
$comment Show the parameter values. $end
$dumpall
$end
#0
$dumpvars
b0 +
bx *
b10 )
b10010101000001010110011 (
b10010101000001010110011 '
b10 &
bx %
b0 $
x#
1"
x!
$end
#20
b100 &
b100 )
b1000000010110101000001100110011 '
b1000000010110101000001100110011 (
#40
b11 &
b11 )
b10010101001001010110011 '
b10010101001001010110011 (
#60
0!
b11 $
b11 +
b10 &
b10 )
b100000100110011000001110000011 '
b100000100110011000001110000011 (
#80
0!
b10 &
b10 )
b1110110110100001111001100000011 '
b1110110110100001111001100000011 (
#100
1!
b0 &
b0 )
b1111010101101101011010000011 '
b1111010101101101011010000011 (
#120
0!
b111 &
b111 )
b1111010101101011011010000011 '
b1111010101101011011010000011 (
#140
b1 $
b1 +
x!
b11 &
b11 )
b1111010101101011011010110111 '
b1111010101101011011010110111 (
#160
b100 $
b100 +
bx &
bx )
b1111010101101010011010100011 '
b1111010101101010011010100011 (
#180
b101 %
b101 *
b101 $
b101 +
b1111010101101111011011100011 '
b1111010101101111011011100011 (
#200
b10 %
b10 *
b1111010101101100011011100011 '
b1111010101101100011011100011 (
#220
1#
b10 $
b10 +
bx %
bx *
b1111010101101111011011101111 '
b1111010101101111011011101111 (
