ALU/ALU.v
/*

The module implements the ALU for the processor.
The ALU comprises of the following function table

    Function        |       alu_ctrl
    BITWISE AND             0000
    BITWISE OR              0001
    ADD                     0010
    SHIFT LEFT              0011
    SUB                     0100
    SHIFT RIGHT             0101
    MULTIPLY                0110
    BITWISE XOR             0111
    SET ON LESS THAN        1000

*/

module ALU (
    input[7:0] in1, in2,
    input[3:0] alu_ctrl,
    output reg[7:0] alu_result,
    output reg zero_flag

);

    always@(*)
        begin
            case (alu_ctrl)
                4'b0000 : alu_result = in1 & in2;
                4'b0001 : alu_result = in1 | in2;
                4'b0010 : alu_result = in1 + in2;
                4'b0011 : alu_result = in1 << in2;
                4'b0100 : alu_result = in1 - in2;
                4'b0101 : alu_result = in1 >> in2;
                4'b0110 : alu_result = in1 * in2;
                4'b0111 : alu_result = in1 ^ in2;
                4'b1000 : begin
                    if(in1 < in2)
                        alu_result = 1;
                    else
                        alu_result = 0;
                end 
            endcase

        if(alu_result == 0)
            assign zero_flag = 1'b1;
        else
            assign zero_flag = 1'b0;

        end




endmodule

ALU/ALU_tb.v
`timescale 1ns/1ns
`include "ALU.v"

module ALU_tb;

reg[7:0] in1, in2;
reg[3:0] alu_ctrl;
wire[7:0] alu_result;
wire zero_flag;

ALU alu(in1, in2, alu_ctrl, alu_result, zero_flag);

initial begin
    $dumpfile("ALU_tb.vcd");
    $dumpvars(0, ALU_tb);

    in1 = 8'b00000101; in2 = 8'b00000110; alu_ctrl = 4'b0000;
    #20;

    in1 = 8'b00000101; in2 = 8'b00000110; alu_ctrl = 4'b0001;
    #20;

    in1 = 8'b00000101; in2 = 8'b00000110; alu_ctrl = 4'b0010;
    #20;

    in1 = 8'b00000101; in2 = 8'b00000110; alu_ctrl = 4'b0011;
    #20;

    in1 = 8'b00000101; in2 = 8'b00000110; alu_ctrl = 4'b0100;
    #20;

    in1 = 8'b00000101; in2 = 8'b00000110; alu_ctrl = 4'b0101;
    #20;

    in1 = 8'b00000101; in2 = 8'b00000110; alu_ctrl = 4'b0110;
    #20;

    in1 = 8'b00000101; in2 = 8'b00000110; alu_ctrl = 4'b0111;
    #20;

    in1 = 8'b00000101; in2 = 8'b00000110; alu_ctrl = 4'b1000;
    #20;

    $display("Test complete!");

end

endmodule

ALU/ALU_tb.vcd
$date
	Sun Feb 25 11:54:59 2024
$end
$version
	Icarus Verilog
$end
$timescale
	1ns
$end
$scope module ALU_tb $end
$var wire 1 ! zero_flag $end
$var wire 8 " alu_result [7:0] $end
$var reg 4 # alu_ctrl [3:0] $end
$var reg 8 $ in1 [7:0] $end
$var reg 8 % in2 [7:0] $end
$scope module alu $end
$var wire 4 & alu_ctrl [3:0] $end
$var wire 8 ' in1 [7:0] $end
$var wire 8 ( in2 [7:0] $end
$var reg 8 ) alu_result [7:0] $end
$var reg 1 ! zero_flag $end
$upscope $end
$upscope $end
$enddefinitions $end
$comment Show the parameter values. $end
$dumpall
$end
#0
$dumpvars
b100 )
b110 (
b101 '
b0 &
b110 %
b101 $
b0 #
b100 "
0!
$end
#20
b111 "
b111 )
b1 #
b1 &
#40
b1011 "
b1011 )
b10 #
b10 &
#60
b1000000 "
b1000000 )
b11 #
b11 &
#80
b11111111 "
b11111111 )
b100 #
b100 &
#100
1!
b0 "
b0 )
b101 #
b101 &
#120
0!
b11110 "
b11110 )
b110 #
b110 &
#140
b11 "
b11 )
b111 #
b111 &
#160
b1 "
b1 )
b1000 #
b1000 &
